{
    "AngelList": 120,
    "Gamasutra": 0,
    "Dribble": 0,
    "Employbl": 0,
    "Google": 159,
    "Government Jobs": 1,
    "Github": 0,
    "Glassdoor": 296,
    "Hired": 0,
    "Intern Supply": 0,
    "Indeed": 893,
    "Greenhouse": 3040,
    "Huntr Jobs": 0,
    "Jopwell": 0,
    "Lever": 2658,
    "LinkedIn": 6568,
    "SimplyHired": 27,
    "Jobvite": 382,
    "Monster": 4,
    "SmartRecruiters": 69,
    "Stella": 0,
    "Triplebyte": 13,
    "Tech Ladies": 2,
    "Underdog": 0,
    "Stackoverflow": 2,
    "Wayup": 0,
    "YCombinator Jobs": 0,
    "Who Is Hiring?": 0,
    "Work At A Startup": 4,
    "Company Website": 1800,
    "ZipRecruiter": 66,
    "Unknown": 3896
}